jiter-0.6.0.dist-info/METADATA
jiter-0.6.0.dist-info/WHEEL
jiter/__init__.py
jiter/__init__.pyi
jiter/py.typed
jiter/jiter.cpython-311-darwin.so
jiter-0.6.0.dist-info/RECORD
