Metadata-Version: 2.3
Name: jiter
Version: 0.6.0
Classifier: Development Status :: 4 - Beta
Classifier: Programming Language :: Python
Classifier: Programming Language :: Python :: 3
Classifier: Programming Language :: Python :: 3 :: Only
Classifier: Programming Language :: Python :: 3.8
Classifier: Programming Language :: Python :: 3.9
Classifier: Programming Language :: Python :: 3.10
Classifier: Programming Language :: Python :: 3.11
Classifier: Programming Language :: Python :: 3.12
Classifier: Intended Audience :: Developers
Classifier: Intended Audience :: Information Technology
Classifier: Intended Audience :: System Administrators
Classifier: License :: OSI Approved :: MIT License
Classifier: Operating System :: Unix
Classifier: Operating System :: POSIX :: Linux
Classifier: Environment :: Console
Classifier: Environment :: MacOS X
Classifier: Topic :: File Formats :: JSON
Classifier: Framework :: Pydantic :: 2
Summary: Fast iterable JSON parser.
Keywords: JSON,parsing,deserialization,iter
Home-Page: https://github.com/pydantic/jiter/
Author: Samuel Colvin <samuel@pydantic.dev>
Author-email: Samuel Colvin <s@muelcolvin.com>
License: MIT
Requires-Python: >=3.8
Project-URL: Source Code, https://github.com/pydantic/jiter/
